{
  "case_id": "broken_baseline_clinical_004",
  "run": 3,
  "condition": "baseline",
  "critic_raw": "",
  "defender_raw": "",
  "adjudication_raw": "Review: Sepsis prediction model comparison.\n\nVerdict: critique_wins\n\nThe AUROC gap of 0.86 vs. 0.71 is inflated by three compounding methodological problems: window-selection advantage (ML evaluated at best point over 6 hours; qSOFA at single triage point), information advantage (lactate/WBC features available mid-window but not at triage), and purpose mismatch (surveillance tool vs. triage tool). These are design choices confirmed in the paper's own methods. The comparison does not support the claimed 'major advance in early sepsis recognition.'",
  "verdict": "critique_wins",
  "issues_found": ["time_horizon_mismatch", "feature_availability_mismatch", "triage_vs_surveillance_baseline_misalignment"],
  "all_issues_raised": ["time_horizon_mismatch", "feature_availability_mismatch", "triage_vs_surveillance_baseline_misalignment"],
  "empirical_test": null
}
