{
  "case_id": "hidden_confounding_ads_market_210",
  "run": 3,
  "condition": "isolated_debate",
  "critic_raw": "CRITIQUE:\n\n1. AUCTION_POLICY_CONFOUND: Reserve-price increases for under-monetized commerce categories mechanically raise RPM.\n2. ADVERTISER_BUDGET_SURGE: Holiday budget doubling and broader match expansion increase auction competition and CPC.\n3. NO_SHADOW_AUCTION: Aggregate RPM conflates model, policy, and market effects without a fixed-conditions counterfactual.",
  "defender_raw": "DEFENSE:\n\nI acknowledge the three confounds. Auction revenue in sponsored search is not a clean measure of model quality when bids, budgets, and reserve prices change simultaneously. The multi-task architecture and stable ad quality metrics are real but do not establish the causal attribution. A shadow auction is the correct test.",
  "adjudication_raw": "Both parties agree on the auction-market attribution problem. critique_wins.",
  "verdict": "critique_wins",
  "issues_found": ["auction_policy_confound", "advertiser_budget_surge", "no_shadow_auction"],
  "all_issues_raised": ["auction_policy_confound", "advertiser_budget_surge", "no_shadow_auction"],
  "empirical_test": null
}
