{
  "case_id": "metric_mismatch_search_018",
  "run": 2,
  "condition": "multiround_debate",
  "critic_raw": "Round 1 Critique:\n1. (relevance_metric_not_resolution_metric) NDCG@10 doesn't predict ticket deflection.\n2. (offline_online_gap_for_ticket_deflection) Offline-online gap uncharacterized for this outcome.\n3. (query_mix_business_alignment_unknown) No query-mix stratification.",
  "defender_raw": "Round 1 Defense:\n1. NDCG@10 with specialist labels is a strong metric.\n2. 11% lift is large.\n3. Latency OK.",
  "adjudication_raw": "After Round 1: All three OPEN.\n\nRound 2:\nCritic Mode 2: The deployment decision is specifically to replace production before a major product release — the most conservative possible moment to introduce new infrastructure. The three issues collectively mean the offline result may not predict user outcomes. This is exactly the scenario where a small online experiment before the major release would be appropriate.\n\nDefender Mode 2: A small pre-launch experiment may not be feasible given the migration cost (re-indexing, retraining editorial workflows). The team argues the offline result is strong enough to proceed.\n\nOrchestrator: The migration cost argument cuts both ways — the higher the migration cost, the more important it is to validate the online outcome before committing. If the NDCG improvement doesn't translate to ticket deflection, the costly migration produces no business benefit. The three issues are not resolved.\n\nAll three force-resolved: critique sustained.\n\nFinal verdict: critique_wins",
  "verdict": "critique_wins",
  "issues_found": ["relevance_metric_not_resolution_metric", "offline_online_gap_for_ticket_deflection", "query_mix_business_alignment_unknown"],
  "all_issues_raised": ["relevance_metric_not_resolution_metric", "offline_online_gap_for_ticket_deflection", "query_mix_business_alignment_unknown"],
  "empirical_test": null,
  "debate_rounds": 2,
  "points_resolved": [],
  "points_force_resolved": ["relevance_metric_not_resolution_metric", "offline_online_gap_for_ticket_deflection", "query_mix_business_alignment_unknown"]
}
