{
  "case_id": "metric_mismatch_survival_020",
  "run": 3,
  "condition": "baseline",
  "critic_raw": "BASELINE ASSESSMENT:\n\nThe concordance index is the standard metric for survival model development, and the paper is correct to use it as the primary scientific metric. However, the paper's deployment claim — that the model is suitable for triaging referrals into a capacity-constrained supportive-care program — requires evidence the paper does not provide.\n\nAt 12% referral capacity, decision-makers need: PPV within the top-12% score distribution, sensitivity at the 12% budget, and decision-curve net benefit weighing true-positive gains against false-positive costs (misallocated nurse and social-work capacity). These are fundamentally different from global concordance. A model can have excellent global rank accuracy while the specific patients just above the 12% threshold boundary are ranked with high uncertainty.\n\nAdditional gaps: lead time from model flag to death is not reported, so it is unknown whether flagged patients are identified early enough for meaningful supportive care enrollment. The existing clinical heuristic (unplanned admissions + ECOG decline) is not evaluated, so incremental value over current practice is unknown.\n\nThe external validation at a second center and routine EHR feature availability are genuine scientific strengths. They do not fill the operational evaluation gap.\n\nVerdict: critique_wins.",
  "verdict": "critique_wins",
  "issues_found": ["c_index_not_triage_metric", "net_benefit_and_capacity_missing", "lead_time_relevance_unreported", "no_clinician_heuristic_comparison"],
  "all_issues_raised": ["c_index_not_triage_metric", "net_benefit_and_capacity_missing", "lead_time_relevance_unreported", "no_clinician_heuristic_comparison"],
  "empirical_test": null
}
